oddscalculator/__init__.py
oddscalculator-0.3.dist-info/DESCRIPTION.rst
oddscalculator-0.3.dist-info/METADATA
oddscalculator-0.3.dist-info/RECORD
oddscalculator-0.3.dist-info/WHEEL
oddscalculator-0.3.dist-info/metadata.json
oddscalculator-0.3.dist-info/top_level.txt
