Metadata-Version: 2.0
Name: oddscalculator
Version: 0.3
Summary: Calculator for decimal, malay, american, hongkong, indonesian odds
Home-page: https://github.com/simopopov/odds_calculator.git
Author: Simeon Popov
Author-email: simopopov@gmail.com
License: MIT
Platform: UNKNOWN
